teachingtoolshed/__init__.py
teachingtoolshed/api/__init__.py
teachingtoolshed/api/edstem.py
teachingtoolshed/gradebook/__init__.py
teachingtoolshed/gradebook/canvas.py
teachingtoolshed/gradebook/csv_readers.py
teaching_toolshed-0.2.12.dist-info/LICENSE
teaching_toolshed-0.2.12.dist-info/WHEEL
teaching_toolshed-0.2.12.dist-info/METADATA
teaching_toolshed-0.2.12.dist-info/RECORD
