Metadata-Version: 2.1
Name: teaching-toolshed
Version: 0.2.12
Summary: Helpful libraries for running classes
Home-page: https://github.com/hschafer/teaching-toolshed
License: MIT
Author: Hunter Schafer
Author-email: hschafer@uw.edu
Requires-Python: >=3.10,<4.0
Classifier: License :: OSI Approved :: MIT License
Classifier: Programming Language :: Python :: 3
Classifier: Programming Language :: Python :: 3.10
Requires-Dist: pandas (>=2.1.0,<3.0.0)
Requires-Dist: pre-commit (>=3.6.0,<4.0.0)
Requires-Dist: requests (>=2.28.1,<3.0.0)
Project-URL: Repository, https://github.com/hschafer/teaching-toolshed
